dxgiss/DXGISS.dll
dxgiss/__init__.py
dxgiss-0.1.0.dist-info/METADATA
dxgiss-0.1.0.dist-info/WHEEL
dxgiss-0.1.0.dist-info/top_level.txt
dxgiss-0.1.0.dist-info/RECORD
