Metadata-Version: 2.4
Name: dxgiss
Version: 0.1.0
Summary: A Python Package to ScreenShot Using DXGI API
Author: zaixia108
Project-URL: homepage, https://github.com/zaixia108/DXGISS
Classifier: Programming Language :: Python :: 3
Classifier: License :: OSI Approved :: MIT License
Classifier: Operating System :: Microsoft :: Windows
Requires-Python: >=3.8
Requires-Dist: numpy
